odf_cli-0.1.1.dist-info/licenses/LICENSE
src/OdfEdit.py
src/odf_converter_cli.py
src/resources/BackgroundRegion.png
src/resources/BitmapNum.png
src/resources/EnclosureStyle.png
src/resources/GoObjectsTemplates.txt
src/resources/Help.txt
src/resources/HwObjectsAttributesCodes.txt
src/resources/HwObjectsAttributesDict.txt
src/resources/HwObjectsTypesList.txt
src/resources/ImageNumButton.png
src/resources/ImageNumLabel.png
src/resources/NotesMidiKeys.png
src/resources/OdfEdit.ico
src/resources/OdfEdit.png
odf_cli-0.1.1.dist-info/METADATA
odf_cli-0.1.1.dist-info/WHEEL
odf_cli-0.1.1.dist-info/entry_points.txt
odf_cli-0.1.1.dist-info/top_level.txt
odf_cli-0.1.1.dist-info/RECORD
