Metadata-Version: 2.4
Name: odf-cli
Version: 0.1.1
Summary: Ferramenta de linha de comando para converter arquivos de definição de órgão do Hauptwerk para o formato GrandOrgue.
Author: Eric Turpault
License:                     GNU GENERAL PUBLIC LICENSE
Keywords: organ,ODF,GrandOrgue,Hauptwerk
Requires-Python: >=3.10
License-File: LICENSE
Requires-Dist: fire
Requires-Dist: lxml
Dynamic: license-file
